cream/__init__.py
cream/_version.py
cream/model.py
cream/util.py
cream_python-1.0.2.dist-info/LICENSE
cream_python-1.0.2.dist-info/METADATA
cream_python-1.0.2.dist-info/NOTICE
cream_python-1.0.2.dist-info/WHEEL
cream_python-1.0.2.dist-info/top_level.txt
cream_python-1.0.2.dist-info/RECORD
