Metadata-Version: 2.1
Name: cream-python
Version: 1.0.2
Summary: Visually-Situated Natural Language Understanding with Contrastive Reading Model and Frozen Large Language Models
Author: Geewook Kim, Hodong Lee, Daehee Kim, Haeji Jung, Sanghee Park, Yoonsik Kim, Sangdoo Yun, Taeho Kil, Bado Lee, Seunghyun Park
Author-email: gwkim.rsrch@gmail.com
License: MIT
Requires-Python: >=3.8
License-File: LICENSE
License-File: NOTICE
Requires-Dist: torch
Requires-Dist: transformers ==4.34.1
Requires-Dist: timm >=0.8.3.dev0
Requires-Dist: pytorch-lightning <=1.9.5,>=1.8.6
Requires-Dist: sentencepiece
Requires-Dist: Pillow
Requires-Dist: lmdb
